inspora_rasa/__init__.py
inspora_rasa/fuzzy_synonym_matcher.py
inspora_rasa/negations.py
inspora_rasa/price.py
inspora_rasa_utilities-0.0.4.dist-info/METADATA
inspora_rasa_utilities-0.0.4.dist-info/WHEEL
inspora_rasa_utilities-0.0.4.dist-info/top_level.txt
inspora_rasa_utilities-0.0.4.dist-info/RECORD
